ezephys/__init__.py
ezephys/pltools.py
ezephys/pltools_test.py
ezephys/rectools.py
ezephys/rectools_test.py
ezephys/stimtools.py
ezephys/stimtools_test.py
ezephys-0.4.3.dist-info/LICENSE.txt
ezephys-0.4.3.dist-info/METADATA
ezephys-0.4.3.dist-info/WHEEL
ezephys-0.4.3.dist-info/top_level.txt
ezephys-0.4.3.dist-info/RECORD
